README.rst
setup.cfg
setup.py
paperweight/__init__.py
paperweight/document.py
paperweight/gitio.py
paperweight/nlputils.py
paperweight/texutils.py
paperweight.egg-info/PKG-INFO
paperweight.egg-info/SOURCES.txt
paperweight.egg-info/dependency_links.txt
paperweight.egg-info/pbr.json
paperweight.egg-info/requires.txt
paperweight.egg-info/top_level.txt