Metadata-Version: 1.1
Name: paperweight
Version: 0.1.1
Summary: Tools for hacking LaTeX documents
Home-page: https://github.com/jonathansick/paperweight
Author: Jonathan Sick
Author-email: jonathansick@mac.com
License: BSD
Platform: UNKNOWN
Classifier: Development Status :: 3 - Alpha
Classifier: Programming Language :: Python
Classifier: Programming Language :: Python :: 2
Classifier: Programming Language :: Python :: 2.7
Classifier: Environment :: Console
